[{"keyword": "fiz", "traffic": 13.51, "difficulty": 29.16}, {"keyword": "fizstream, llc", "traffic": 4.92, "difficulty": 12.47}, {"keyword": "mk flex", "traffic": 5.14, "difficulty": 32.78}, {"keyword": "my flex", "traffic": 1.06, "difficulty": 33.32}, {"keyword": "myflex", "traffic": 2.08, "difficulty": 54.54}, {"keyword": "myflexfund", "traffic": 1.32, "difficulty": 4.82}, {"keyword": "my flex spending", "traffic": 2.33, "difficulty": 33.03}, {"keyword": "my flex time", "traffic": 0.8, "difficulty": 31.91}, {"keyword": "my stream", "traffic": 1.06, "difficulty": 39.05}, {"keyword": "mystream", "traffic": 3.54, "difficulty": 38.0}, {"keyword": "pro-flex llc", "traffic": 1.32, "difficulty": 35.28}]