[{"keyword": "app multiservice", "traffic": 1.06, "difficulty": 36.81}, {"keyword": "big brother the game", "traffic": 1.06, "difficulty": 30.59}, {"keyword": "datv", "traffic": 4.92, "difficulty": 26.95}, {"keyword": "ds tv", "traffic": 7.29, "difficulty": 29.86}, {"keyword": "dstv", "traffic": 32.14, "difficulty": 25.5}, {"keyword": "multiservice", "traffic": 1.06, "difficulty": 38.29}, {"keyword": "my dstv app", "traffic": 8.3, "difficulty": 25.32}, {"keyword": "mydstv app", "traffic": 14.0, "difficulty": 25.32}]