[{"keyword": "bank of maldives", "traffic": 4.92, "difficulty": 41.62}, {"keyword": "honeyfund", "traffic": 1.57, "difficulty": 40.3}, {"keyword": "honeyminer", "traffic": 1.57, "difficulty": 44.33}, {"keyword": "honeymoon", "traffic": 1.57, "difficulty": 40.68}, {"keyword": "lily", "traffic": 5.8, "difficulty": 48.79}, {"keyword": "lily beach", "traffic": 1.32, "difficulty": 13.55}, {"keyword": "lily hotels pvt ltd", "traffic": 1.57, "difficulty": 4.82}, {"keyword": "lilys", "traffic": 1.83, "difficulty": 49.13}, {"keyword": "maldives", "traffic": 6.45, "difficulty": 45.96}, {"keyword": "maldivian", "traffic": 7.29, "difficulty": 41.44}, {"keyword": "royalton luxury resorts", "traffic": 1.32, "difficulty": 37.82}]