[{"keyword": "aereomexico", "traffic": 2.57, "difficulty": 29.37}, {"keyword": "aeromexico", "traffic": 12.68, "difficulty": 28.61}, {"keyword": "aerom\u00e9xico", "traffic": 30.79, "difficulty": 29.86}, {"keyword": "aeromexico app", "traffic": 2.33, "difficulty": 27.89}, {"keyword": "air mexico", "traffic": 2.08, "difficulty": 31.32}, {"keyword": "areomexico", "traffic": 2.57, "difficulty": 29.57}, {"keyword": "auromexico", "traffic": 2.57, "difficulty": 29.27}, {"keyword": "bolaris", "traffic": 4.01, "difficulty": 26.65}, {"keyword": "car service", "traffic": 1.57, "difficulty": 59.52}, {"keyword": "carservice", "traffic": 2.57, "difficulty": 57.83}, {"keyword": "gms", "traffic": 12.51, "difficulty": 35.41}, {"keyword": "la mexicana express", "traffic": 1.57, "difficulty": 22.68}, {"keyword": "lembert computer technologies", "traffic": 6.66, "difficulty": 31.7}, {"keyword": "mexicana car service yonkers", "traffic": 2.57, "difficulty": 15.29}, {"keyword": "payattitude digital", "traffic": 2.57, "difficulty": 14.47}, {"keyword": "toa taxis", "traffic": 2.57, "difficulty": 57.77}, {"keyword": "to!taxi", "traffic": 2.57, "difficulty": 57.75}, {"keyword": "vit car service", "traffic": 5.14, "difficulty": 57.86}]