[{"keyword": "august", "traffic": 14.63, "difficulty": 54.97}, {"keyword": "augusta national, inc.", "traffic": 11.83, "difficulty": 49.31}, {"keyword": "august lock", "traffic": 6.87, "difficulty": 48.34}, {"keyword": "august smart lock", "traffic": 16.6, "difficulty": 48.34}, {"keyword": "dental", "traffic": 8.5, "difficulty": 57.07}, {"keyword": "dental drugs", "traffic": 3.06, "difficulty": 57.07}, {"keyword": "dentistry", "traffic": 0.8, "difficulty": 45.0}, {"keyword": "diradiology", "traffic": 3.77, "difficulty": 53.33}, {"keyword": "pros-consulte", "traffic": 2.33, "difficulty": 39.22}, {"keyword": "radiography", "traffic": 1.57, "difficulty": 48.53}, {"keyword": "radiology", "traffic": 1.57, "difficulty": 48.33}, {"keyword": "radiology toolbox lite", "traffic": 0.53, "difficulty": 48.24}, {"keyword": "radiopedia", "traffic": 1.57, "difficulty": 48.36}, {"keyword": "realworld radiology", "traffic": 0.53, "difficulty": 48.31}]