[{"keyword": "auction", "traffic": 15.71, "difficulty": 56.48}, {"keyword": "auction access", "traffic": 14.79, "difficulty": 56.5}, {"keyword": "auction cars", "traffic": 6.02, "difficulty": 56.51}, {"keyword": "auction.com", "traffic": 13.84, "difficulty": 56.54}, {"keyword": "auction games", "traffic": 6.87, "difficulty": 56.49}, {"keyword": "auctionzip", "traffic": 8.89, "difficulty": 56.48}, {"keyword": "aution", "traffic": 2.33, "difficulty": 56.55}, {"keyword": "auto auction", "traffic": 1.32, "difficulty": 56.34}, {"keyword": "bancomer mexico", "traffic": 1.32, "difficulty": 23.9}, {"keyword": "bancomer m\u00f3vil", "traffic": 1.57, "difficulty": 28.38}, {"keyword": "bbv", "traffic": 4.92, "difficulty": 34.69}, {"keyword": "bbva colombia", "traffic": 14.95, "difficulty": 52.72}, {"keyword": "bbva mexico", "traffic": 15.71, "difficulty": 33.77}, {"keyword": "bbva m\u00e9xico", "traffic": 1.06, "difficulty": 25.32}, {"keyword": "bbva movil", "traffic": 1.57, "difficulty": 27.37}, {"keyword": "bbva peru", "traffic": 17.88, "difficulty": 25.68}, {"keyword": "bbva per\u00fa", "traffic": 1.32, "difficulty": 25.68}, {"keyword": "bidding", "traffic": 6.66, "difficulty": 56.9}, {"keyword": "bva", "traffic": 14.0, "difficulty": 36.19}, {"keyword": "bva app", "traffic": 7.29, "difficulty": 26.5}, {"keyword": "bva auctions", "traffic": 14.0, "difficulty": 26.95}, {"keyword": "bvva", "traffic": 10.58, "difficulty": 34.09}, {"keyword": "catawiki", "traffic": 2.57, "difficulty": 24.34}, {"keyword": "catawiki - online auctions", "traffic": 2.57, "difficulty": 24.55}, {"keyword": "e auction", "traffic": 12.17, "difficulty": 56.53}, {"keyword": "eauction.ge", "traffic": 15.71, "difficulty": 23.9}, {"keyword": "faille", "traffic": 2.57, "difficulty": 18.37}, {"keyword": "lauritz.com \u2013 online auctions", "traffic": 2.33, "difficulty": 42.68}, {"keyword": "opgt", "traffic": 10.21, "difficulty": 54.1}, {"keyword": "ovm", "traffic": 14.0, "difficulty": 29.16}, {"keyword": "pierce the veil", "traffic": 1.06, "difficulty": 40.68}, {"keyword": "provincial", "traffic": 3.06, "difficulty": 42.51}, {"keyword": "provinet", "traffic": 1.32, "difficulty": 24.75}, {"keyword": "proxibid", "traffic": 4.47, "difficulty": 56.49}, {"keyword": "rbauction", "traffic": 13.51, "difficulty": 56.59}, {"keyword": "social deal - the best deals", "traffic": 0.27, "difficulty": 48.12}, {"keyword": "troostwijk auctions", "traffic": 2.57, "difficulty": 7.65}, {"keyword": "vakantieveilingen - dagje uit", "traffic": 10.58, "difficulty": 24.12}, {"keyword": "veil", "traffic": 4.47, "difficulty": 41.22}, {"keyword": "veiled", "traffic": 12.0, "difficulty": 41.6}]