[{"keyword": "airplay tv", "traffic": 2.08, "difficulty": 47.08}, {"keyword": "aople tv", "traffic": 6.24, "difficulty": 43.66}, {"keyword": "appke tv", "traffic": 2.57, "difficulty": 43.76}, {"keyword": "appleairplay", "traffic": 1.57, "difficulty": 34.35}, {"keyword": "appletv +", "traffic": 1.57, "difficulty": 45.0}, {"keyword": "apple tv keyboard", "traffic": 6.66, "difficulty": 43.77}, {"keyword": "apple tv mls", "traffic": 2.57, "difficulty": 43.77}, {"keyword": "apple tv plus", "traffic": 0.8, "difficulty": 43.69}, {"keyword": "applr tv", "traffic": 2.57, "difficulty": 43.86}, {"keyword": "apply tv", "traffic": 2.33, "difficulty": 44.16}, {"keyword": "appollo tv", "traffic": 1.57, "difficulty": 43.31}, {"keyword": "ap tv", "traffic": 7.29, "difficulty": 45.13}, {"keyword": "bruit blanc", "traffic": 2.57, "difficulty": 39.51}, {"keyword": "campfire", "traffic": 9.46, "difficulty": 38.81}, {"keyword": "canpfire", "traffic": 2.57, "difficulty": 37.82}, {"keyword": "coyzy", "traffic": 4.92, "difficulty": 43.45}, {"keyword": "cozy christmas fireplace.", "traffic": 0.8, "difficulty": 15.29}, {"keyword": "cozy cozy", "traffic": 9.84, "difficulty": 43.17}, {"keyword": "cozy fireplaces hd", "traffic": 1.32, "difficulty": 22.68}, {"keyword": "cozy tv fireplace", "traffic": 2.57, "difficulty": 18.37}, {"keyword": "duo tv", "traffic": 2.57, "difficulty": 29.06}, {"keyword": "fier tv", "traffic": 2.33, "difficulty": 40.85}, {"keyword": "firelight", "traffic": 1.57, "difficulty": 45.31}, {"keyword": "fire place", "traffic": 1.57, "difficulty": 42.14}, {"keyword": "fireplace", "traffic": 4.01, "difficulty": 41.11}, {"keyword": "fireplace 3d lite", "traffic": 1.83, "difficulty": 40.55}, {"keyword": "fireplace live hd", "traffic": 2.33, "difficulty": 40.57}, {"keyword": "fireplace remote", "traffic": 3.77, "difficulty": 40.3}, {"keyword": "fire rv", "traffic": 1.32, "difficulty": 40.15}, {"keyword": "firet", "traffic": 2.08, "difficulty": 46.02}, {"keyword": "fire tb", "traffic": 3.77, "difficulty": 40.57}, {"keyword": "fire tv", "traffic": 28.64, "difficulty": 41.55}, {"keyword": "fire tv app", "traffic": 1.57, "difficulty": 40.15}, {"keyword": "fire tv cast", "traffic": 0.8, "difficulty": 40.84}, {"keyword": "fire tv & fire stick mirroring", "traffic": 2.08, "difficulty": 41.55}, {"keyword": "fire tv mirror", "traffic": 1.32, "difficulty": 40.24}, {"keyword": "fite tv", "traffic": 7.29, "difficulty": 41.49}, {"keyword": "frie tv", "traffic": 2.57, "difficulty": 40.49}, {"keyword": "fure tv", "traffic": 4.92, "difficulty": 40.32}, {"keyword": "henry schein", "traffic": 2.57, "difficulty": 26.18}, {"keyword": "langman", "traffic": 2.57, "difficulty": 43.31}, {"keyword": "log fire", "traffic": 2.08, "difficulty": 27.77}, {"keyword": "ohub campfire", "traffic": 14.0, "difficulty": 37.09}, {"keyword": "pokemon campfire", "traffic": 1.32, "difficulty": 37.7}, {"keyword": "relax-tv", "traffic": 1.57, "difficulty": 31.09}, {"keyword": "tvos", "traffic": 13.51, "difficulty": 43.41}, {"keyword": "web for apple tv - web browser", "traffic": 2.08, "difficulty": 43.17}, {"keyword": "wood tv 8", "traffic": 1.32, "difficulty": 26.8}, {"keyword": "woodtv 8", "traffic": 2.33, "difficulty": 26.8}, {"keyword": "zeniko", "traffic": 2.57, "difficulty": 28.73}, {"keyword": "zenoki ltd", "traffic": 2.57, "difficulty": 18.37}]