[{"keyword": "angie pro leads", "traffic": 2.08, "difficulty": 61.16}, {"keyword": "capture leads", "traffic": 2.57, "difficulty": 37.32}, {"keyword": "cvent leadcapture", "traffic": 15.26, "difficulty": 23.67}, {"keyword": "d expo", "traffic": 4.69, "difficulty": 57.67}, {"keyword": "eacts lead capture", "traffic": 4.69, "difficulty": 37.25}, {"keyword": "exhibitor s&p scans", "traffic": 5.14, "difficulty": 41.16}, {"keyword": "expe", "traffic": 2.57, "difficulty": 57.83}, {"keyword": "expo", "traffic": 5.14, "difficulty": 57.75}, {"keyword": "expo app", "traffic": 1.57, "difficulty": 57.72}, {"keyword": "expo client", "traffic": 3.06, "difficulty": 57.69}, {"keyword": "expo inc", "traffic": 3.3, "difficulty": 44.91}, {"keyword": "expos", "traffic": 1.57, "difficulty": 58.34}, {"keyword": "icapture powerscan", "traffic": 6.66, "difficulty": 20.5}, {"keyword": "leada", "traffic": 2.33, "difficulty": 61.12}, {"keyword": "leadar", "traffic": 1.57, "difficulty": 61.02}, {"keyword": "lead capture", "traffic": 1.32, "difficulty": 37.51}, {"keyword": "lead retrieval", "traffic": 3.77, "difficulty": 36.56}, {"keyword": "leads", "traffic": 3.77, "difficulty": 61.14}, {"keyword": "leidsa", "traffic": 7.29, "difficulty": 61.86}, {"keyword": "stova", "traffic": 6.02, "difficulty": 37.05}, {"keyword": "stova lead capture", "traffic": 6.87, "difficulty": 18.37}, {"keyword": "trad inc.", "traffic": 3.77, "difficulty": 48.18}]