[{"keyword": "a food truck:food maker game", "traffic": 2.82, "difficulty": 30.92}, {"keyword": "flavor maker", "traffic": 4.47, "difficulty": 32.12}, {"keyword": "frostie", "traffic": 1.32, "difficulty": 38.03}, {"keyword": "frosty", "traffic": 3.77, "difficulty": 39.02}, {"keyword": "froyo", "traffic": 4.92, "difficulty": 33.99}, {"keyword": "frozen yogurt", "traffic": 6.66, "difficulty": 37.25}, {"keyword": "ice cream game", "traffic": 13.51, "difficulty": 55.22}, {"keyword": "icecream game", "traffic": 2.57, "difficulty": 55.19}, {"keyword": "ice cream truck", "traffic": 0.27, "difficulty": 54.39}, {"keyword": "ice fever", "traffic": 0.53, "difficulty": 33.21}, {"keyword": "icy", "traffic": 13.18, "difficulty": 42.34}, {"keyword": "icy dessert maker", "traffic": 13.18, "difficulty": 31.01}, {"keyword": "icy & spicy katowice", "traffic": 3.06, "difficulty": 42.21}, {"keyword": "kids fun plus", "traffic": 3.3, "difficulty": 45.84}, {"keyword": "manny's sweet treats", "traffic": 1.57, "difficulty": 36.15}, {"keyword": "mechies", "traffic": 2.57, "difficulty": 37.82}, {"keyword": "menchie's", "traffic": 4.69, "difficulty": 23.44}, {"keyword": "menchies", "traffic": 14.0, "difficulty": 37.85}, {"keyword": "mining fever", "traffic": 2.33, "difficulty": 42.83}, {"keyword": "pink berry", "traffic": 1.83, "difficulty": 23.67}, {"keyword": "pinkberry", "traffic": 4.92, "difficulty": 22.41}, {"keyword": "popsicle", "traffic": 2.57, "difficulty": 39.54}, {"keyword": "popsicle game", "traffic": 2.08, "difficulty": 38.84}, {"keyword": "sundae", "traffic": 1.57, "difficulty": 50.61}, {"keyword": "sundaes gelato dessert", "traffic": 0.53, "difficulty": 16.69}, {"keyword": "sweet shapp", "traffic": 1.32, "difficulty": 46.57}, {"keyword": "tcby", "traffic": 14.0, "difficulty": 16.03}, {"keyword": "yogurt", "traffic": 5.8, "difficulty": 41.18}, {"keyword": "yogurt app", "traffic": 1.32, "difficulty": 40.51}, {"keyword": "yogurtland", "traffic": 13.84, "difficulty": 24.94}, {"keyword": "yogurt mountain", "traffic": 6.66, "difficulty": 17.85}]