[{"keyword": "bankers trust", "traffic": 4.01, "difficulty": 49.34}, {"keyword": "bank of billings", "traffic": 2.08, "difficulty": 51.7}, {"keyword": "bank with united", "traffic": 3.06, "difficulty": 40.74}, {"keyword": "bankwithunited", "traffic": 4.01, "difficulty": 40.74}, {"keyword": "billpay", "traffic": 2.57, "difficulty": 51.81}, {"keyword": "kansas", "traffic": 2.82, "difficulty": 51.65}, {"keyword": "khc mobile app", "traffic": 8.5, "difficulty": 53.03}, {"keyword": "ks* app", "traffic": 4.24, "difficulty": 52.41}, {"keyword": "ks bank inc.", "traffic": 7.29, "difficulty": 33.5}, {"keyword": "ks go", "traffic": 10.21, "difficulty": 53.8}, {"keyword": "ks mobile banking", "traffic": 6.24, "difficulty": 33.55}, {"keyword": "ks mobile, inc.", "traffic": 13.35, "difficulty": 52.42}, {"keyword": "ksmu mobile", "traffic": 12.85, "difficulty": 52.4}, {"keyword": "my bank first united mobile", "traffic": 0.53, "difficulty": 25.13}, {"keyword": "omnify benefits", "traffic": 3.77, "difficulty": 15.29}, {"keyword": "somerset trust bank", "traffic": 0.8, "difficulty": 49.3}, {"keyword": "the bank and trust", "traffic": 0.53, "difficulty": 47.19}, {"keyword": "the bank ks", "traffic": 1.32, "difficulty": 33.55}, {"keyword": "trast", "traffic": 2.57, "difficulty": 60.16}, {"keyword": "trist", "traffic": 3.06, "difficulty": 60.14}, {"keyword": "triust bank", "traffic": 6.45, "difficulty": 49.48}, {"keyword": "trus", "traffic": 2.57, "difficulty": 60.15}, {"keyword": "trushot", "traffic": 1.57, "difficulty": 59.71}, {"keyword": "trust", "traffic": 7.9, "difficulty": 59.79}, {"keyword": "trust and will", "traffic": 0.27, "difficulty": 52.8}, {"keyword": "trust-app", "traffic": 1.32, "difficulty": 60.22}, {"keyword": "trustar bank", "traffic": 0.8, "difficulty": 49.3}, {"keyword": "trustar bank mobile banking", "traffic": 0.8, "difficulty": 49.29}, {"keyword": "trust axiata pay", "traffic": 5.14, "difficulty": 32.91}, {"keyword": "trust bank", "traffic": 3.06, "difficulty": 49.48}, {"keyword": "trusted", "traffic": 1.06, "difficulty": 60.12}, {"keyword": "trustee", "traffic": 0.8, "difficulty": 60.3}, {"keyword": "trustly", "traffic": 1.57, "difficulty": 60.14}, {"keyword": "trustly group ab", "traffic": 1.32, "difficulty": 60.08}, {"keyword": "trustoa", "traffic": 0.8, "difficulty": 59.82}, {"keyword": "trustvault", "traffic": 1.57, "difficulty": 60.08}, {"keyword": "trvst", "traffic": 7.29, "difficulty": 60.08}, {"keyword": "tryst", "traffic": 14.0, "difficulty": 59.72}, {"keyword": "turst", "traffic": 6.66, "difficulty": 60.11}, {"keyword": "ubt", "traffic": 13.18, "difficulty": 30.33}, {"keyword": "ubt go", "traffic": 15.71, "difficulty": 30.5}, {"keyword": "ubt retirement", "traffic": 10.58, "difficulty": 15.29}, {"keyword": "ubt sports complex", "traffic": 14.0, "difficulty": 14.47}, {"keyword": "ucb", "traffic": 13.51, "difficulty": 43.08}, {"keyword": "unikase", "traffic": 0.53, "difficulty": 64.24}, {"keyword": "unit-app :)", "traffic": 2.08, "difficulty": 64.2}, {"keyword": "unite", "traffic": 1.57, "difficulty": 66.85}, {"keyword": "unitear", "traffic": 1.57, "difficulty": 64.14}, {"keyword": "united bank", "traffic": 3.54, "difficulty": 40.78}, {"keyword": "united community bank", "traffic": 0.53, "difficulty": 40.89}, {"keyword": "uniteen", "traffic": 1.57, "difficulty": 64.15}, {"keyword": "uniters", "traffic": 1.57, "difficulty": 64.15}, {"keyword": "unitly", "traffic": 2.57, "difficulty": 65.41}, {"keyword": "usht app", "traffic": 4.69, "difficulty": 64.06}]