[{"keyword": "big bang whip", "traffic": 3.77, "difficulty": 38.26}, {"keyword": "ehip", "traffic": 14.0, "difficulty": 38.92}, {"keyword": "gameflex", "traffic": 1.32, "difficulty": 38.92}, {"keyword": "indiana jones whip", "traffic": 5.14, "difficulty": 38.81}, {"keyword": "i whip", "traffic": 8.1, "difficulty": 38.87}, {"keyword": "lash extensions game", "traffic": 7.29, "difficulty": 31.17}, {"keyword": "latigo", "traffic": 2.57, "difficulty": 38.46}, {"keyword": "pocket whi", "traffic": 4.69, "difficulty": 39.15}, {"keyword": "pocket whio", "traffic": 5.8, "difficulty": 38.81}, {"keyword": "pokit wip", "traffic": 5.59, "difficulty": 38.87}, {"keyword": "real whip", "traffic": 1.32, "difficulty": 38.79}, {"keyword": "rope weapon", "traffic": 0.8, "difficulty": 21.19}, {"keyword": "sheldon's whip", "traffic": 1.57, "difficulty": 38.81}, {"keyword": "slave whip", "traffic": 6.45, "difficulty": 38.81}, {"keyword": "smack dat ass", "traffic": 2.08, "difficulty": 39.79}, {"keyword": "the whip", "traffic": 7.08, "difficulty": 38.52}, {"keyword": "the whip sound app original", "traffic": 1.83, "difficulty": 38.73}, {"keyword": "whil", "traffic": 6.87, "difficulty": 39.93}, {"keyword": "whip", "traffic": 40.35, "difficulty": 39.0}, {"keyword": "whip all", "traffic": 2.82, "difficulty": 38.87}, {"keyword": "whip alp", "traffic": 3.77, "difficulty": 38.87}, {"keyword": "whip ap", "traffic": 1.32, "difficulty": 38.79}, {"keyword": "whip app", "traffic": 2.57, "difficulty": 38.81}, {"keyword": "whipapp", "traffic": 2.57, "difficulty": 38.76}, {"keyword": "whip clean", "traffic": 1.32, "difficulty": 38.26}, {"keyword": "whip cracking", "traffic": 2.82, "difficulty": 38.94}, {"keyword": "whipe", "traffic": 2.57, "difficulty": 38.79}, {"keyword": "whip game", "traffic": 2.08, "difficulty": 38.79}, {"keyword": "whip game!", "traffic": 1.57, "difficulty": 33.83}, {"keyword": "whiping app", "traffic": 2.57, "difficulty": 38.97}, {"keyword": "whip it", "traffic": 1.57, "difficulty": 38.87}, {"keyword": "whip me", "traffic": 1.57, "difficulty": 38.81}, {"keyword": "whip noise", "traffic": 4.01, "difficulty": 38.87}, {"keyword": "whipp", "traffic": 1.57, "difficulty": 38.94}, {"keyword": "whipped!", "traffic": 1.57, "difficulty": 38.97}, {"keyword": "whipper", "traffic": 2.08, "difficulty": 39.1}, {"keyword": "whipping app", "traffic": 2.57, "difficulty": 38.73}, {"keyword": "whips", "traffic": 2.57, "difficulty": 38.41}, {"keyword": "whip simulator", "traffic": 4.47, "difficulty": 38.76}, {"keyword": "whip swing", "traffic": 1.06, "difficulty": 16.69}, {"keyword": "wipapp", "traffic": 7.29, "difficulty": 38.81}, {"keyword": "wipp", "traffic": 8.89, "difficulty": 39.15}, {"keyword": "wipping app", "traffic": 7.29, "difficulty": 38.76}]