[{"keyword": "ai audio", "traffic": 2.57, "difficulty": 41.33}, {"keyword": "ai boice", "traffic": 1.32, "difficulty": 43.53}, {"keyword": "aiic voices", "traffic": 4.92, "difficulty": 43.3}, {"keyword": "ai music", "traffic": 6.87, "difficulty": 47.33}, {"keyword": "ai music pro", "traffic": 2.08, "difficulty": 46.97}, {"keyword": "ai sound", "traffic": 2.08, "difficulty": 36.26}, {"keyword": "ai voice", "traffic": 8.69, "difficulty": 48.39}, {"keyword": "aivoice", "traffic": 15.71, "difficulty": 42.75}, {"keyword": "ai voices", "traffic": 4.69, "difficulty": 48.17}, {"keyword": "audiofix", "traffic": 1.57, "difficulty": 49.25}, {"keyword": "audiofix: for videos + volume", "traffic": 1.32, "difficulty": 26.18}, {"keyword": "barrett foster", "traffic": 1.32, "difficulty": 16.69}, {"keyword": "boice ai", "traffic": 4.69, "difficulty": 42.84}, {"keyword": "bye noise", "traffic": 2.57, "difficulty": 26.02}, {"keyword": "byenoise", "traffic": 16.89, "difficulty": 25.13}, {"keyword": "byenoise - denoise video audio", "traffic": 11.65, "difficulty": 25.13}, {"keyword": "clearvoice", "traffic": 0.8, "difficulty": 27.23}, {"keyword": "coice ai", "traffic": 4.24, "difficulty": 42.81}, {"keyword": "deepdenoise", "traffic": 2.57, "difficulty": 24.12}, {"keyword": "denoise", "traffic": 6.66, "difficulty": 31.09}, {"keyword": "denoise audio", "traffic": 4.69, "difficulty": 25.5}, {"keyword": "denoise me", "traffic": 2.08, "difficulty": 30.41}, {"keyword": "foster", "traffic": 2.57, "difficulty": 44.82}, {"keyword": "fosters", "traffic": 4.69, "difficulty": 44.41}, {"keyword": "inverse.ai", "traffic": 3.3, "difficulty": 27.23}, {"keyword": "krispcall", "traffic": 3.3, "difficulty": 24.94}, {"keyword": "lauda app", "traffic": 2.08, "difficulty": 40.91}, {"keyword": "moises ai", "traffic": 9.27, "difficulty": 32.53}, {"keyword": "moises audio", "traffic": 6.66, "difficulty": 44.23}, {"keyword": "noise reducer", "traffic": 9.08, "difficulty": 38.41}, {"keyword": "noise reduction", "traffic": 3.77, "difficulty": 34.83}, {"keyword": "noisewall", "traffic": 1.57, "difficulty": 23.67}, {"keyword": "photo noise reduction", "traffic": 0.27, "difficulty": 31.7}, {"keyword": "reduct", "traffic": 1.06, "difficulty": 44.29}, {"keyword": "reducto", "traffic": 1.32, "difficulty": 43.86}, {"keyword": "remove text from video", "traffic": 1.57, "difficulty": 31.62}, {"keyword": "smartmike+", "traffic": 1.32, "difficulty": 25.13}, {"keyword": "somar", "traffic": 2.33, "difficulty": 44.43}, {"keyword": "sonarr", "traffic": 6.45, "difficulty": 43.16}, {"keyword": "sonqar", "traffic": 4.24, "difficulty": 42.89}, {"keyword": "the fax: a + send & receive", "traffic": 7.49, "difficulty": 38.68}, {"keyword": "video noise reducer", "traffic": 1.32, "difficulty": 22.94}, {"keyword": "vioce ai", "traffic": 1.57, "difficulty": 43.45}, {"keyword": "vocie ai", "traffic": 5.8, "difficulty": 42.87}, {"keyword": "voice ai", "traffic": 3.06, "difficulty": 42.63}, {"keyword": "voice.ai", "traffic": 3.3, "difficulty": 48.41}, {"keyword": "voiceai", "traffic": 1.32, "difficulty": 42.87}, {"keyword": "voice ai free", "traffic": 1.57, "difficulty": 42.09}, {"keyword": "vouce ai", "traffic": 4.24, "difficulty": 42.72}]