[{"keyword": "eregio", "traffic": 3.06, "difficulty": 43.37}, {"keyword": "m radio", "traffic": 12.17, "difficulty": 42.18}, {"keyword": "ms radio", "traffic": 2.57, "difficulty": 45.46}, {"keyword": "my uu", "traffic": 2.57, "difficulty": 25.32}, {"keyword": "myuu", "traffic": 4.92, "difficulty": 25.13}, {"keyword": "r\u00e9gi\u00f3 r\u00e1di\u00f3", "traffic": 0.8, "difficulty": 17.3}, {"keyword": "rtl nieuws", "traffic": 2.33, "difficulty": 53.38}, {"keyword": "r tv", "traffic": 4.92, "difficulty": 43.16}, {"keyword": "rtv", "traffic": 12.85, "difficulty": 37.82}, {"keyword": "rtv.", "traffic": 0.8, "difficulty": 35.87}, {"keyword": "rtv slovenija", "traffic": 9.08, "difficulty": 41.01}, {"keyword": "rtv utrecht", "traffic": 6.24, "difficulty": 12.47}]