[{"keyword": "barn manager", "traffic": 4.24, "difficulty": 35.67}, {"keyword": "bigemap\u5730\u7403-\u5b9e\u666f\u4e09\u7ef4\u536b\u661f\u5730\u56fe", "traffic": 5.14, "difficulty": 24.75}, {"keyword": "china consular affairs", "traffic": 0.27, "difficulty": 22.12}, {"keyword": "din tai fung", "traffic": 12.17, "difficulty": 16.69}, {"keyword": "discerning hearts", "traffic": 2.57, "difficulty": 22.12}, {"keyword": "efteling", "traffic": 13.35, "difficulty": 26.95}, {"keyword": "horsemanager", "traffic": 0.53, "difficulty": 25.5}, {"keyword": "qing qing yu", "traffic": 14.0, "difficulty": 42.68}, {"keyword": "yu gao", "traffic": 5.59, "difficulty": 45.68}, {"keyword": "yuyu zhang", "traffic": 9.84, "difficulty": 50.06}, {"keyword": "yu zhang", "traffic": 5.8, "difficulty": 50.01}]