[{"keyword": "ecloud", "traffic": 2.57, "difficulty": 45.51}, {"keyword": "epad", "traffic": 6.45, "difficulty": 31.62}, {"keyword": "epas", "traffic": 3.54, "difficulty": 30.92}, {"keyword": "e pass", "traffic": 14.0, "difficulty": 54.6}, {"keyword": "epass", "traffic": 14.79, "difficulty": 54.6}, {"keyword": "epass.mobile", "traffic": 0.8, "difficulty": 54.57}, {"keyword": "passapp, inc", "traffic": 0.53, "difficulty": 45.16}, {"keyword": "passapp taxi", "traffic": 3.3, "difficulty": 66.47}, {"keyword": "tong zhang", "traffic": 1.57, "difficulty": 44.43}]