[{"keyword": "care hub mobile", "traffic": 1.32, "difficulty": 31.32}, {"keyword": "corn hub", "traffic": 1.32, "difficulty": 35.11}, {"keyword": "omni", "traffic": 6.87, "difficulty": 49.75}, {"keyword": "omnic+", "traffic": 1.57, "difficulty": 20.5}, {"keyword": "omnicaas", "traffic": 0.53, "difficulty": 20.85}, {"keyword": "omni care", "traffic": 0.27, "difficulty": 18.37}, {"keyword": "omnicare hub", "traffic": 0.8, "difficulty": 7.65}, {"keyword": "omni.healthcare", "traffic": 3.3, "difficulty": 18.85}, {"keyword": "secure hub by citrix", "traffic": 4.92, "difficulty": 38.46}, {"keyword": "the text hub", "traffic": 1.32, "difficulty": 28.02}]