[{"keyword": "10% happier inc.", "traffic": 0.53, "difficulty": 36.56}, {"keyword": "10 percent happier", "traffic": 0.53, "difficulty": 37.29}, {"keyword": "al friend", "traffic": 2.57, "difficulty": 37.88}, {"keyword": "autosleep", "traffic": 4.47, "difficulty": 37.29}, {"keyword": "bamba", "traffic": 2.57, "difficulty": 37.82}, {"keyword": "bamba bbq", "traffic": 0.53, "difficulty": 36.81}, {"keyword": "be care", "traffic": 6.66, "difficulty": 39.54}, {"keyword": "be focused", "traffic": 9.46, "difficulty": 35.06}, {"keyword": "befocused", "traffic": 3.77, "difficulty": 35.06}, {"keyword": "be focused - focus timer", "traffic": 10.76, "difficulty": 35.02}, {"keyword": "be focused pro", "traffic": 3.77, "difficulty": 35.02}, {"keyword": "behappier", "traffic": 1.57, "difficulty": 33.94}, {"keyword": "behappiness", "traffic": 2.57, "difficulty": 33.61}, {"keyword": "be happy", "traffic": 1.06, "difficulty": 41.55}, {"keyword": "behappy", "traffic": 1.57, "difficulty": 35.67}, {"keyword": "be mindful", "traffic": 2.57, "difficulty": 33.61}, {"keyword": "be-style", "traffic": 7.7, "difficulty": 42.19}, {"keyword": "be tracker", "traffic": 1.83, "difficulty": 39.61}, {"keyword": "bey et", "traffic": 5.59, "difficulty": 47.86}, {"keyword": "bumba", "traffic": 2.33, "difficulty": 38.12}, {"keyword": "calm timer", "traffic": 1.57, "difficulty": 40.22}, {"keyword": "day by day \u2014 mood tracker", "traffic": 1.83, "difficulty": 31.99}, {"keyword": "dayla", "traffic": 2.08, "difficulty": 36.98}, {"keyword": "daylia", "traffic": 1.57, "difficulty": 35.5}, {"keyword": "daylio", "traffic": 15.86, "difficulty": 35.87}, {"keyword": "daylio journal", "traffic": 4.69, "difficulty": 33.55}, {"keyword": "daylo", "traffic": 4.24, "difficulty": 36.6}, {"keyword": "delio journal", "traffic": 2.57, "difficulty": 33.55}, {"keyword": "e-calman", "traffic": 5.59, "difficulty": 40.24}, {"keyword": "flo fitness", "traffic": 1.06, "difficulty": 37.29}, {"keyword": "happiness, mindfulness journal", "traffic": 0.8, "difficulty": 28.26}, {"keyword": "happy-note", "traffic": 1.06, "difficulty": 32.84}, {"keyword": "headsmart", "traffic": 1.57, "difficulty": 46.28}, {"keyword": "headspace", "traffic": 17.46, "difficulty": 46.35}, {"keyword": "headspace free", "traffic": 0.8, "difficulty": 43.95}, {"keyword": "hugging face", "traffic": 4.24, "difficulty": 38.38}, {"keyword": "kuki", "traffic": 15.1, "difficulty": 39.73}, {"keyword": "meditopia", "traffic": 1.57, "difficulty": 35.15}, {"keyword": "meditopia: sleep, meditation", "traffic": 1.32, "difficulty": 30.76}, {"keyword": "mood journal tracker-mood note", "traffic": 2.08, "difficulty": 32.53}, {"keyword": "mood tracker self care journal", "traffic": 1.32, "difficulty": 36.98}, {"keyword": "m\u00fasica para dormir", "traffic": 1.57, "difficulty": 37.67}, {"keyword": "myreplika", "traffic": 2.08, "difficulty": 38.57}, {"keyword": "petit bambou", "traffic": 9.46, "difficulty": 29.27}, {"keyword": "reflection - note reflections", "traffic": 1.06, "difficulty": 30.5}, {"keyword": "reflectly - journal & ai diary", "traffic": 2.57, "difficulty": 39.05}, {"keyword": "relika", "traffic": 2.57, "difficulty": 38.63}, {"keyword": "relpika", "traffic": 7.29, "difficulty": 38.54}, {"keyword": "repika", "traffic": 4.92, "difficulty": 38.57}, {"keyword": "repilka", "traffic": 6.87, "difficulty": 38.57}, {"keyword": "replica ai", "traffic": 3.06, "difficulty": 38.84}, {"keyword": "replika", "traffic": 17.18, "difficulty": 38.57}, {"keyword": "replika ai", "traffic": 1.83, "difficulty": 38.65}, {"keyword": "respirelax+", "traffic": 2.57, "difficulty": 29.67}, {"keyword": "self-reflection", "traffic": 0.53, "difficulty": 37.12}, {"keyword": "sleep watch by bodymatter", "traffic": 3.77, "difficulty": 40.37}, {"keyword": "talia: secret diary notes", "traffic": 2.57, "difficulty": 37.15}, {"keyword": "talk to ai", "traffic": 3.54, "difficulty": 36.19}, {"keyword": "talk to a robot", "traffic": 6.02, "difficulty": 39.05}, {"keyword": "ten percent", "traffic": 4.01, "difficulty": 31.55}, {"keyword": "ten percent happier", "traffic": 13.02, "difficulty": 37.19}, {"keyword": "tenpercenthappier", "traffic": 6.24, "difficulty": 27.37}, {"keyword": "teplika", "traffic": 12.17, "difficulty": 38.57}, {"keyword": "ti'be", "traffic": 2.08, "difficulty": 26.65}, {"keyword": "ti inspire", "traffic": 4.92, "difficulty": 35.79}, {"keyword": "top sant\u00e9 magazine", "traffic": 1.32, "difficulty": 32.97}, {"keyword": "veta", "traffic": 4.92, "difficulty": 48.08}, {"keyword": "vita-health", "traffic": 4.01, "difficulty": 38.15}, {"keyword": "vladislav budruev", "traffic": 4.24, "difficulty": 16.69}, {"keyword": "watchnote+", "traffic": 0.27, "difficulty": 37.02}, {"keyword": "watchnotes", "traffic": 1.06, "difficulty": 37.79}, {"keyword": "zenia", "traffic": 2.57, "difficulty": 34.4}, {"keyword": "zina", "traffic": 6.45, "difficulty": 33.44}, {"keyword": "zinia", "traffic": 6.66, "difficulty": 34.45}, {"keyword": "zinni", "traffic": 2.33, "difficulty": 31.17}, {"keyword": "zinnia", "traffic": 15.56, "difficulty": 30.76}, {"keyword": "\u0628\u0627\u0645\u0628\u0648 - bambo", "traffic": 1.32, "difficulty": 42.63}]