[{"keyword": "aprende cultura general", "traffic": 1.57, "difficulty": 39.77}, {"keyword": "area quiz", "traffic": 1.57, "difficulty": 25.68}, {"keyword": "banco provincia", "traffic": 0.53, "difficulty": 43.0}, {"keyword": "de italiaan", "traffic": 2.57, "difficulty": 37.29}, {"keyword": "dinero rapido", "traffic": 1.57, "difficulty": 44.52}, {"keyword": "dinero rapido provincial", "traffic": 4.47, "difficulty": 44.01}, {"keyword": "iriparo", "traffic": 4.92, "difficulty": 39.25}, {"keyword": "las provincias", "traffic": 2.08, "difficulty": 42.6}, {"keyword": "michal ivaska", "traffic": 4.24, "difficulty": 17.85}, {"keyword": "provincial", "traffic": 3.06, "difficulty": 42.04}, {"keyword": "quiz it", "traffic": 0.8, "difficulty": 45.59}, {"keyword": "quiz it game", "traffic": 1.06, "difficulty": 43.88}, {"keyword": "quiz it - gk booster", "traffic": 7.49, "difficulty": 44.98}, {"keyword": "quiz - provinces of italy", "traffic": 1.57, "difficulty": 7.65}, {"keyword": "sigla, s.a", "traffic": 7.29, "difficulty": 32.97}, {"keyword": "siglo 21", "traffic": 2.57, "difficulty": 33.32}]