[{"keyword": "arthur & aziliz", "traffic": 5.14, "difficulty": 54.72}, {"keyword": "auto rotate", "traffic": 0.53, "difficulty": 55.7}, {"keyword": "byrotation", "traffic": 11.48, "difficulty": 57.01}, {"keyword": "circular", "traffic": 1.57, "difficulty": 55.42}, {"keyword": "clideo", "traffic": 4.92, "difficulty": 55.73}, {"keyword": "clipp", "traffic": 2.82, "difficulty": 50.01}, {"keyword": "crop and trim video", "traffic": 3.54, "difficulty": 55.7}, {"keyword": "cropic", "traffic": 2.57, "difficulty": 59.3}, {"keyword": "cropit", "traffic": 2.57, "difficulty": 59.28}, {"keyword": "crop people out", "traffic": 2.57, "difficulty": 59.26}, {"keyword": "crop photo free", "traffic": 3.06, "difficulty": 52.23}, {"keyword": "crop pictures", "traffic": 6.87, "difficulty": 59.28}, {"keyword": "cropping app", "traffic": 2.57, "difficulty": 59.35}, {"keyword": "cropping pictures", "traffic": 2.57, "difficulty": 56.17}, {"keyword": "crop scouting", "traffic": 0.8, "difficulty": 59.27}, {"keyword": "cropvideo", "traffic": 2.57, "difficulty": 55.68}, {"keyword": "crop video free", "traffic": 1.57, "difficulty": 52.14}, {"keyword": "crop videos", "traffic": 0.8, "difficulty": 56.79}, {"keyword": "crop water", "traffic": 1.57, "difficulty": 55.75}, {"keyword": "desenvolver", "traffic": 1.06, "difficulty": 53.73}, {"keyword": "edusurd", "traffic": 2.57, "difficulty": 51.99}, {"keyword": "faceless portrait", "traffic": 2.82, "difficulty": 53.89}, {"keyword": "fipp", "traffic": 10.94, "difficulty": 49.23}, {"keyword": "fix and flip", "traffic": 3.77, "difficulty": 31.24}, {"keyword": "fix app by fix.com", "traffic": 8.89, "difficulty": 59.73}, {"keyword": "fix blurry photo", "traffic": 14.32, "difficulty": 47.52}, {"keyword": "fix blurry video", "traffic": 3.54, "difficulty": 47.62}, {"keyword": "fix old photos", "traffic": 3.54, "difficulty": 46.02}, {"keyword": "fix photos", "traffic": 2.33, "difficulty": 46.29}, {"keyword": "fix pictures", "traffic": 6.24, "difficulty": 46.25}, {"keyword": "fix&repair", "traffic": 4.69, "difficulty": 59.73}, {"keyword": "fix the photo", "traffic": 19.24, "difficulty": 46.33}, {"keyword": "flip and dive", "traffic": 1.06, "difficulty": 52.16}, {"keyword": "flip and dress", "traffic": 0.27, "difficulty": 51.84}, {"keyword": "flip camera", "traffic": 1.32, "difficulty": 43.98}, {"keyword": "fliper zero", "traffic": 2.57, "difficulty": 49.89}, {"keyword": "flipexplorer", "traffic": 1.57, "difficulty": 49.25}, {"keyword": "flip gram", "traffic": 1.32, "difficulty": 44.02}, {"keyword": "flip images", "traffic": 0.27, "difficulty": 44.47}, {"keyword": "flipit", "traffic": 3.54, "difficulty": 51.14}, {"keyword": "flippa", "traffic": 0.53, "difficulty": 49.85}, {"keyword": "flippad", "traffic": 1.32, "difficulty": 50.35}, {"keyword": "flipper", "traffic": 2.33, "difficulty": 49.42}, {"keyword": "flipper mobile app", "traffic": 0.8, "difficulty": 49.33}, {"keyword": "flipper zero", "traffic": 4.01, "difficulty": 49.31}, {"keyword": "flip photo", "traffic": 1.57, "difficulty": 44.65}, {"keyword": "flip picture", "traffic": 1.57, "difficulty": 44.42}, {"keyword": "flipp norge", "traffic": 0.53, "difficulty": 48.95}, {"keyword": "flipps", "traffic": 1.57, "difficulty": 49.24}, {"keyword": "flipps media inc.", "traffic": 1.57, "difficulty": 48.98}, {"keyword": "flipp - weekly shopping", "traffic": 1.32, "difficulty": 49.19}, {"keyword": "flippz", "traffic": 1.57, "difficulty": 48.98}, {"keyword": "flip video", "traffic": 1.57, "difficulty": 47.43}, {"keyword": "flipz", "traffic": 2.08, "difficulty": 49.07}, {"keyword": "flupper", "traffic": 5.14, "difficulty": 49.27}, {"keyword": "flypp", "traffic": 4.47, "difficulty": 49.16}, {"keyword": "free landscaping app", "traffic": 0.53, "difficulty": 47.91}, {"keyword": "icrop", "traffic": 2.57, "difficulty": 59.27}, {"keyword": "kapwing resizer", "traffic": 4.69, "difficulty": 48.68}, {"keyword": "land scape", "traffic": 1.57, "difficulty": 53.18}, {"keyword": "landscape", "traffic": 3.77, "difficulty": 53.23}, {"keyword": "landscape planner", "traffic": 3.54, "difficulty": 52.54}, {"keyword": "landscaper & tree pro business", "traffic": 0.53, "difficulty": 52.72}, {"keyword": "led banner - led scroller \u207a", "traffic": 0.53, "difficulty": 33.03}, {"keyword": "ledboard", "traffic": 4.24, "difficulty": 34.2}, {"keyword": "led scroller : led banner text", "traffic": 1.32, "difficulty": 31.09}, {"keyword": "lil flippers", "traffic": 2.57, "difficulty": 49.26}, {"keyword": "lipp", "traffic": 2.57, "difficulty": 52.89}, {"keyword": "orientate", "traffic": 7.08, "difficulty": 51.54}, {"keyword": "orionitas", "traffic": 1.57, "difficulty": 53.67}, {"keyword": "perfect video", "traffic": 3.54, "difficulty": 53.43}, {"keyword": "photo and picture resizer", "traffic": 1.06, "difficulty": 47.87}, {"keyword": "photo crop editor", "traffic": 1.57, "difficulty": 55.92}, {"keyword": "photo cropping", "traffic": 1.57, "difficulty": 56.8}, {"keyword": "photo fixer", "traffic": 4.69, "difficulty": 46.84}, {"keyword": "photo flipper", "traffic": 0.27, "difficulty": 44.06}, {"keyword": "photo resize", "traffic": 2.57, "difficulty": 49.52}, {"keyword": "photo resizer", "traffic": 1.06, "difficulty": 48.06}, {"keyword": "photo resolution", "traffic": 2.08, "difficulty": 50.39}, {"keyword": "photo rotate", "traffic": 0.53, "difficulty": 44.55}, {"keyword": "photo shrinker", "traffic": 1.32, "difficulty": 48.57}, {"keyword": "pic resize", "traffic": 2.57, "difficulty": 47.9}, {"keyword": "portrait", "traffic": 9.46, "difficulty": 53.92}, {"keyword": "portrait editor", "traffic": 3.3, "difficulty": 51.17}, {"keyword": "portrait mode", "traffic": 1.57, "difficulty": 53.72}, {"keyword": "potrait", "traffic": 2.57, "difficulty": 53.9}, {"keyword": "pro landscape", "traffic": 2.57, "difficulty": 52.72}, {"keyword": "pro landscape home", "traffic": 4.24, "difficulty": 52.58}, {"keyword": "pro landscaper", "traffic": 1.32, "difficulty": 52.71}, {"keyword": "qflipper", "traffic": 22.12, "difficulty": 49.31}, {"keyword": "reebee", "traffic": 5.14, "difficulty": 49.15}, {"keyword": "resize", "traffic": 1.57, "difficulty": 50.22}, {"keyword": "resize for instagram", "traffic": 1.32, "difficulty": 48.77}, {"keyword": "resize photo app", "traffic": 6.87, "difficulty": 47.91}, {"keyword": "resize photos", "traffic": 1.06, "difficulty": 47.56}, {"keyword": "resize - photo.s and video.s !", "traffic": 18.3, "difficulty": 46.79}, {"keyword": "resize : photo & video edit.or", "traffic": 0.53, "difficulty": 47.62}, {"keyword": "resize picture", "traffic": 1.83, "difficulty": 48.52}, {"keyword": "resize video", "traffic": 1.57, "difficulty": 47.26}, {"keyword": "rfv", "traffic": 10.58, "difficulty": 25.68}, {"keyword": "rotacion de pantalla", "traffic": 4.24, "difficulty": 22.68}, {"keyword": "rotate", "traffic": 1.06, "difficulty": 55.85}, {"keyword": "rotate and roll", "traffic": 2.33, "difficulty": 55.82}, {"keyword": "rotate picture", "traffic": 4.24, "difficulty": 48.73}, {"keyword": "rotate screen", "traffic": 6.45, "difficulty": 43.16}, {"keyword": "rotate video & flip", "traffic": 2.82, "difficulty": 43.33}, {"keyword": "rotatic", "traffic": 0.53, "difficulty": 55.6}, {"keyword": "rotatio", "traffic": 0.8, "difficulty": 56.9}, {"keyword": "rotation", "traffic": 4.69, "difficulty": 57.01}, {"keyword": "rotation control", "traffic": 9.84, "difficulty": 56.87}, {"keyword": "rotator", "traffic": 1.57, "difficulty": 55.8}, {"keyword": "rotator 3d", "traffic": 1.57, "difficulty": 55.79}, {"keyword": "rotat\u00f3ria", "traffic": 0.53, "difficulty": 55.78}, {"keyword": "rotator lite", "traffic": 0.8, "difficulty": 55.75}, {"keyword": "screen rotation", "traffic": 1.32, "difficulty": 66.78}, {"keyword": "self portrait", "traffic": 1.57, "difficulty": 53.94}, {"keyword": "shrink photo", "traffic": 5.14, "difficulty": 48.85}, {"keyword": "shrink video", "traffic": 4.24, "difficulty": 48.37}, {"keyword": "video crop app", "traffic": 1.32, "difficulty": 55.63}, {"keyword": "video cropper", "traffic": 2.08, "difficulty": 55.87}, {"keyword": "video crop - resize video", "traffic": 1.57, "difficulty": 40.85}, {"keyword": "video resolution", "traffic": 1.06, "difficulty": 50.84}, {"keyword": "video rotate", "traffic": 0.8, "difficulty": 43.19}, {"keyword": "video+rotate & flip free", "traffic": 1.32, "difficulty": 43.19}, {"keyword": "viplexhandy", "traffic": 6.87, "difficulty": 45.37}, {"keyword": "wrong", "traffic": 14.16, "difficulty": 45.24}, {"keyword": "y-turn", "traffic": 14.48, "difficulty": 54.31}]