[{"keyword": "animals link onet", "traffic": 0.8, "difficulty": 27.77}, {"keyword": "bakana: onet animal classic", "traffic": 5.37, "difficulty": 29.77}, {"keyword": "link link animals", "traffic": 1.06, "difficulty": 38.87}, {"keyword": "long nguyen", "traffic": 1.06, "difficulty": 38.38}, {"keyword": "ment 2022", "traffic": 2.57, "difficulty": 37.76}, {"keyword": "onet", "traffic": 4.92, "difficulty": 39.54}, {"keyword": "onet animal", "traffic": 1.32, "difficulty": 40.45}, {"keyword": "onet animal deluxe", "traffic": 0.8, "difficulty": 39.39}, {"keyword": "onet animal link new", "traffic": 1.57, "difficulty": 33.77}, {"keyword": "onet connect", "traffic": 3.54, "difficulty": 40.04}, {"keyword": "onet connect animal link", "traffic": 0.53, "difficulty": 27.37}, {"keyword": "onet - connect & match puzzle", "traffic": 2.57, "difficulty": 37.42}, {"keyword": "onet connect pro", "traffic": 0.8, "difficulty": 36.81}, {"keyword": "onet deluxe", "traffic": 1.57, "difficulty": 39.73}, {"keyword": "onet funny animal", "traffic": 0.8, "difficulty": 39.47}, {"keyword": "onet legend", "traffic": 1.06, "difficulty": 39.42}, {"keyword": "onet link animal", "traffic": 1.57, "difficulty": 28.14}, {"keyword": "onet link animals", "traffic": 1.57, "difficulty": 27.77}, {"keyword": "onet picachu", "traffic": 1.83, "difficulty": 42.29}, {"keyword": "onet poczta", "traffic": 3.3, "difficulty": 39.82}, {"keyword": "onet puzzle", "traffic": 3.77, "difficulty": 39.49}, {"keyword": "onet s", "traffic": 1.57, "difficulty": 39.42}, {"keyword": "onnet", "traffic": 2.57, "difficulty": 74.44}, {"keyword": "phi long nguyen", "traffic": 2.57, "difficulty": 34.14}, {"keyword": "pikachu", "traffic": 15.56, "difficulty": 47.42}, {"keyword": "pikachu games", "traffic": 7.9, "difficulty": 45.53}, {"keyword": "qnet mobile wp", "traffic": 14.16, "difficulty": 22.94}]