[{"keyword": "bogged", "traffic": 2.57, "difficulty": 38.63}, {"keyword": "bollt", "traffic": 2.57, "difficulty": 50.01}, {"keyword": "bolt", "traffic": 41.65, "difficulty": 49.96}, {"keyword": "bolt mobile", "traffic": 0.8, "difficulty": 49.94}, {"keyword": "bolt music", "traffic": 4.92, "difficulty": 49.54}, {"keyword": "bolt music downloader", "traffic": 3.3, "difficulty": 49.59}, {"keyword": "bolts", "traffic": 2.57, "difficulty": 49.98}, {"keyword": "bolt taxi", "traffic": 4.47, "difficulty": 49.66}, {"keyword": "bolt taxify", "traffic": 3.54, "difficulty": 49.78}, {"keyword": "bolt usa", "traffic": 1.57, "difficulty": 49.56}, {"keyword": "boltz", "traffic": 2.57, "difficulty": 50.05}, {"keyword": "botl", "traffic": 4.01, "difficulty": 50.12}, {"keyword": "bult", "traffic": 4.92, "difficulty": 51.83}, {"keyword": "buy cryptocurrency", "traffic": 3.54, "difficulty": 43.03}, {"keyword": "buy ethereum", "traffic": 4.47, "difficulty": 42.57}, {"keyword": "faucetpay", "traffic": 16.01, "difficulty": 37.64}, {"keyword": "metamask", "traffic": 14.79, "difficulty": 42.14}, {"keyword": "pancakeswap", "traffic": 6.66, "difficulty": 37.88}, {"keyword": "pankake swap", "traffic": 7.29, "difficulty": 37.67}, {"keyword": "s-crypto, ltd.", "traffic": 12.17, "difficulty": 47.7}, {"keyword": "taxicy", "traffic": 1.57, "difficulty": 50.1}, {"keyword": "taxif", "traffic": 6.45, "difficulty": 50.37}, {"keyword": "taxify", "traffic": 3.3, "difficulty": 50.19}, {"keyword": "taxity", "traffic": 2.08, "difficulty": 50.17}, {"keyword": "teust wallet", "traffic": 12.68, "difficulty": 37.88}, {"keyword": "truat wallet", "traffic": 7.29, "difficulty": 37.85}, {"keyword": "true wallet", "traffic": 1.57, "difficulty": 38.15}, {"keyword": "truist wallet", "traffic": 3.3, "difficulty": 37.64}, {"keyword": "trust: crypto & bitcoin wallet", "traffic": 7.29, "difficulty": 35.58}, {"keyword": "trust walket", "traffic": 1.32, "difficulty": 38.97}, {"keyword": "trust waller", "traffic": 1.32, "difficulty": 38.06}, {"keyword": "trust wallet", "traffic": 33.81, "difficulty": 37.7}, {"keyword": "trustwallet", "traffic": 1.57, "difficulty": 37.76}, {"keyword": "trust wallet dapp", "traffic": 3.54, "difficulty": 37.58}, {"keyword": "trus wallet", "traffic": 2.57, "difficulty": 37.85}, {"keyword": "trx wallet", "traffic": 8.89, "difficulty": 38.46}, {"keyword": "tryst wallet", "traffic": 6.66, "difficulty": 37.88}, {"keyword": "tust wallet", "traffic": 11.48, "difficulty": 37.82}, {"keyword": "ugk wallet", "traffic": 10.58, "difficulty": 33.66}, {"keyword": "wallet connect", "traffic": 1.06, "difficulty": 64.98}, {"keyword": "x.d. global", "traffic": 26.3, "difficulty": 37.29}, {"keyword": "xmedia", "traffic": 4.01, "difficulty": 42.53}, {"keyword": "x-wallet", "traffic": 34.94, "difficulty": 35.63}]