[{"keyword": "g\u00fcnl\u00fck bur\u00e7", "traffic": 8.89, "difficulty": 37.42}, {"keyword": "g\u00fczel s\u00f6zler", "traffic": 7.29, "difficulty": 29.67}, {"keyword": "kapak s\u00f6zler", "traffic": 3.54, "difficulty": 29.86}, {"keyword": "ki\u015fisel geli\u015fim", "traffic": 4.92, "difficulty": 34.3}, {"keyword": "\u00f6zl\u00fc s\u00f6zler", "traffic": 7.9, "difficulty": 29.77}, {"keyword": "resimli s\u00f6zler", "traffic": 1.57, "difficulty": 29.67}, {"keyword": "sevgiliye s\u00f6zler", "traffic": 7.29, "difficulty": 29.67}]